monasca_notification/__init__.py
monasca_notification/config.py
monasca_notification/main.py
monasca_notification/notification.py
monasca_notification/notification_engine.py
monasca_notification/notification_exceptions.py
monasca_notification/periodic_engine.py
monasca_notification/retry_engine.py
monasca_notification/version.py
monasca_notification/common/__init__.py
monasca_notification/common/utils.py
monasca_notification/common/repositories/__init__.py
monasca_notification/common/repositories/exceptions.py
monasca_notification/common/repositories/base/__init__.py
monasca_notification/common/repositories/base/base_repo.py
monasca_notification/common/repositories/mysql/__init__.py
monasca_notification/common/repositories/mysql/mysql_repo.py
monasca_notification/common/repositories/orm/__init__.py
monasca_notification/common/repositories/orm/models.py
monasca_notification/common/repositories/orm/orm_repo.py
monasca_notification/common/repositories/postgres/__init__.py
monasca_notification/common/repositories/postgres/pgsql_repo.py
monasca_notification/conf/__init__.py
monasca_notification/conf/database.py
monasca_notification/conf/kafka.py
monasca_notification/conf/keystone.py
monasca_notification/conf/notifiers.py
monasca_notification/conf/processors.py
monasca_notification/conf/queues.py
monasca_notification/conf/retry.py
monasca_notification/conf/statsd.py
monasca_notification/conf/types.py
monasca_notification/conf/zookeeper.py
monasca_notification/plugins/__init__.py
monasca_notification/plugins/abstract_notifier.py
monasca_notification/plugins/email_notifier.py
monasca_notification/plugins/hipchat_notifier.py
monasca_notification/plugins/jira_notifier.py
monasca_notification/plugins/jiraformat.yml
monasca_notification/plugins/pagerduty_notifier.py
monasca_notification/plugins/slack_notifier.py
monasca_notification/plugins/webhook_notifier.py
monasca_notification/processors/__init__.py
monasca_notification/processors/alarm_processor.py
monasca_notification-9.0.0.dist-info/AUTHORS
monasca_notification-9.0.0.dist-info/LICENSE
monasca_notification-9.0.0.dist-info/METADATA
monasca_notification-9.0.0.dist-info/WHEEL
monasca_notification-9.0.0.dist-info/entry_points.txt
monasca_notification-9.0.0.dist-info/pbr.json
monasca_notification-9.0.0.dist-info/top_level.txt
monasca_notification-9.0.0.dist-info/RECORD
