Metadata-Version: 2.1
Name: monasca-notification
Version: 9.0.0
Summary: Reads alarms from Kafka and then notifies the customer using their configured notification method.
Home-page: https://opendev.org/openstack/monasca-notification
Author: OpenStack
Author-email: openstack-discuss@lists.openstack.org
License: Apache
Keywords: openstack monitoring email
Platform: UNKNOWN
Classifier: Development Status :: 5 - Production/Stable
Classifier: License :: OSI Approved :: Apache Software License
Classifier: Topic :: System :: Monitoring
Classifier: Operating System :: POSIX :: Linux
Classifier: Programming Language :: Python
Classifier: Programming Language :: Python :: Implementation :: CPython
Classifier: Programming Language :: Python :: 3 :: Only
Classifier: Programming Language :: Python :: 3
Classifier: Programming Language :: Python :: 3.6
Classifier: Programming Language :: Python :: 3.7
Classifier: Programming Language :: Python :: 3.8
Requires-Python: >=3.6
Requires-Dist: PyYAML (>=3.13)
Requires-Dist: debtcollector (>=1.2.0)
Requires-Dist: jira (>=2.0.0)
Requires-Dist: keystoneauth1 (>=3.4.0)
Requires-Dist: monasca-common (>=2.16.0)
Requires-Dist: monasca-statsd (>=1.4.0)
Requires-Dist: oslo.config (>=5.2.0)
Requires-Dist: oslo.log (>=3.36.0)
Requires-Dist: oslo.serialization (>=2.18.0)
Requires-Dist: pbr (>=3.1.1)
Requires-Dist: requests (>=2.14.2)
Requires-Dist: simplejson (>=3.8.1)
Provides-Extra: jira_plugin
Requires-Dist: Jinja2 (>=2.10) ; extra == 'jira_plugin'
Provides-Extra: test
Requires-Dist: Babel (!=2.4.0,>=2.3.4) ; extra == 'test'
Requires-Dist: PyMySQL (>=0.7.6) ; extra == 'test'
Requires-Dist: SQLAlchemy (!=1.1.5,!=1.1.6,!=1.1.7,!=1.1.8,>=1.0.10) ; extra == 'test'
Requires-Dist: bandit (!=1.6.0,>=1.1.0) ; extra == 'test'
Requires-Dist: coverage (!=4.4,>=4.0) ; extra == 'test'
Requires-Dist: docutils (>=0.11) ; extra == 'test'
Requires-Dist: hacking (<3.1.0,>=3.0.1) ; extra == 'test'
Requires-Dist: oslotest (>=3.2.0) ; extra == 'test'
Requires-Dist: psycopg2 (>=2.8.4) ; extra == 'test'
Requires-Dist: stestr (>=1.0.0) ; extra == 'test'
Requires-Dist: testrepository (>=0.0.18) ; extra == 'test'
